[{"newCode":"1210126044","title":"中山学林苑","houseurl":"http:\/\/zhongshanxuelinyuan.fang.com\/","zongfen":"4.1","dianpingcount":3,"tao":"0","housetype":"loupan","saling":"2","purpose":"住宅","tejia":false,"xiaoguotu":"效果图","x":"121.43013763427734375000","y":"31.22233390808105468750","price_num":"待定","price_unit":"","picAddress":"http:\/\/img11.soufunimg.com\/viewimage\/house\/2017_08\/03\/M1A\/0C\/2E\/ChCE4VmCgV6IecaZAAK8MXDgDlMAAopQwOOz94AArxJ419\/232x162.jpg","householdpic":"<u>四居<\/u>&#10","adshowurl":"","minarea":160,"maxarea":200,"物业类别":"普通住宅","项目特色":"现房","建筑类别":"塔楼高层","装修状况":"非毛坯,公共部分简单","产权年限":"普通住宅:70年","环线位置":"内环以内","开发商":"颐丰（上海）有限公司","楼盘地址":"定西路1310弄16号","销售状态":"待售","楼盘优惠":"暂无","开盘时间":"待定[开盘时间详情]","交房时间":"预计2017年12月入住","售楼地址":"静安区石门一路288号兴业中心1座38楼","咨询电话":"400-890-0000转843496","主力户型":"四居(4)","预售许可证":"暂无资料","占地面积":"8350平方米","建筑面积":"21717平方米","容积率":"2.60 ","绿化率":"35%","停车位":"暂无资料","楼栋总数":"1栋","总户数":"120户","物业公司":"上海瑞强物业管理有限公司","物业费":"3.00元\/㎡·月 ","楼层状况":"1栋30层","普通住宅:70年":"","轨交":"2号线中山公园站、3\/4号线中山公园站公交","幼儿园":"愚园路第一幼儿园(凯旋路分园)、武夷路幼儿园中小学","中山学林苑项目地处内环内中山公园板块核心区域。项目毗邻4条轨道交通，地铁2,3,4,11号线，这4条线路可以让您畅达全城，感受上海的速度，开车出行同样十分方便。中山学林苑项目紧贴城市中心的森林氧吧——中山公园，它是上海内环内著名的大型公园之一，近在咫尺的森林氧吧，是您和家人在周末或在工作之余，修身养性，闲庭信步的好去处。它带领我们远离都市喧嚣，抛开职场的纷繁，跟至亲一起享受大自然给予的绿色生活。":"","on_the_average":"待定","house_type":1},{"newCode":"1210125216","title":"高和海德公馆","houseurl":"http:\/\/haidegongguangh.fang.com\/","zongfen":"4.7","dianpingcount":35,"tao":"0","housetype":"loupan","saling":"2","purpose":"写字楼","tejia":false,"xiaoguotu":"效果图","x":"121.42748260498046875000","y":"31.22488212585449218750","price_num":"待定","price_unit":"","picAddress":"http:\/\/img6n.soufunimg.com\/viewimage\/house\/2016_10\/31\/M09\/0C\/86\/wKgEUFgWsAKIGnqRAAc9i6SnskcAATknQPyTboABz2j326\/232x162.jpg","householdpic":"<u>楼层平面图<\/u>&#10","adshowurl":"","minarea":0,"maxarea":0,"物业类别":"标准写字楼","楼盘特色":"公园地产","写字楼级别":"其他","楼栋情况":"独栋","产权年限":"50年","环线位置":"内环以内","开发商":"高和资本","所属商圈":"中山公园","楼盘地址":"长宁长宁路833号（近中山公园）[查看地图]","销售状态":"待售","楼盘优惠":"暂无资料","开盘时间":"已于2016年10月1日开盘[开盘时间详情]","交房时间":"预计2018年6月交房[交房时间详情]","售楼地址":"长宁路833号近定西路","咨询电话":"400-890-0000转825918","预售许可证":"暂无资料","占地面积":"9084平方米","建筑面积":"36088平方米","标准层面积":"暂无资料","商业面积":"暂无资料","办公面积":"暂无资料","开间面积":"暂无资料","容积率":"8.50[容积率详情]","标准层高":"暂无资料","绿化率":"10%[绿化率详情]","装修情况":"非毛坯[装修相册][建材市场]","楼层说明":"1栋楼共32层","物业公司":"恺信亚洲","物业费":"13元\/㎡·月","物业说明":"高和海德公馆物业费为13元\/平\/月","供暖方式":"空调、地暖","水电类别":"市政供电,市政供水","停车位配置":"暂无信息","电梯配置":"【电梯数量】客梯2个、货梯1个、扶梯0个","商场或超市":"中山公园龙之梦购物中心、来福士广场（在建）、兆丰广场学校","高和海德公馆地处长宁路定西路交汇处，是由高和资本与同策咨询联手打造的都市公园大宅，项目位于地铁2号线中山公园站上盖；坐拥整个中山公园商圈，交通便利，地标级商业（龙之梦、来福士广场（在建中））、酒店（万丽酒店、新世界酒店、医疗等生活配套一应俱全。":"","on_the_average":"待定","house_type":1}]