[{"newCode":"2620061054","title":"山湖温泉","houseurl":"http:\/\/704342.fang.com\/","zongfen":"3.9","dianpingcount":4,"tao":"0","housetype":"loupan","saling":"1","purpose":"住宅","tejia":false,"xiaoguotu":"效果图","x":"113.93858337402343750000","y":"29.94396209716796875000","price_num":"4600","price_unit":"元\/平","picAddress":"http:\/\/img6n.soufunimg.com\/viewimage\/house\/2017_04\/12\/M07\/0F\/BC\/wKgEUFjt76aIA0FwAAMLr_wOuGQAAYljQFU0ewAAwvH743\/232x162.jpg","householdpic":"<u>一居<\/u>&#10<u>二居<\/u>&#10<u>三居<\/u>&#10","adshowurl":"","minarea":0,"maxarea":0,"物业类别":"普通住宅","项目特色":"复合地产打折优惠楼盘","建筑类别":"板楼低层多层","装修状况":"非毛坯","产权年限":"70","环线位置":"中环以外","开发商":"嘉鱼山湖温泉旅游有限公司","楼盘地址":"咸宁市嘉鱼县鱼月镇连江大道（白湖桥旁）","销售状态":"在售","楼盘优惠":"暂无","开盘时间":"暂无资料[开盘时间详情]","交房时间":"","售楼地址":"武汉广场写字楼1606室（解放大道和武商路交汇处）","咨询电话":"400-890-0000转663021","主力户型":"一居(4)二居(7)三居(1)","预售许可证":"","占地面积":"1600000平方米","建筑面积":"1200000平方米","容积率":"0.50 ","绿化率":"75%","停车位":"1","楼栋总数":"暂无资料","总户数":"300户","物业公司":"澳大利亚IAPA设计顾问有限公司","物业费":"0.90元\/平方米·月 ","楼层状况":"4层","70":"","沿京珠高速公路行驶19.0公里，右前方转弯，行驶50米，左后方转弯进入S101沿S101行驶280米，右转进入S102。沿S102行驶6.7公里，过左侧的加油站约50米后，右前方转弯进入环岛。沿环岛行驶10米，在第1个出口，右前方转弯进入S102。沿S102行驶50.2公里，右前方转弯进入环岛。沿环岛行驶100米，在第3个出口，右前方转弯进入沙阳大道。":"","小区内部配套":"小区健身器材","山湖温泉位于中国温泉之乡咸宁市嘉鱼县三湖连江风景区牛头山景区。22000多亩的湖面，6000多亩的森林公园，1000余亩的湿地，独特的山、水、温泉世界。开发面积2400亩，120万平方米。山湖温泉致力于大造华中乃至全国品质的温泉旅游度假圣地.景区功能划分":"1、温泉区（温泉会所、酒店客房、别墅）；2、地产区（公寓、花园洋房、别墅）；3、湖泊游乐区（水上飞机、游艇等）；4、陆地娱乐区（高尔夫、跑马场、拓展等)；5、佛教文化区（南如禅寺、岳公亭等）6、农业观光（农牧养殖、农家餐饮、土特产）。一期四百亩，分为温泉游乐区，公寓、花园洋房区，别墅区。目前销售的是产权式酒店，产权式酒店就是将酒店的每一个单位分别出售给投资人，同时投资人委托酒店管理公司管理，获取一定的投资回报。投资山湖温泉产权式酒店回报高达10%，其中8%为现金，2%为景区消费券，景区消费券在景区视同现金使用。","on_the_average":"均价约4600元\/平方米","house_type":1},{"newCode":"2620137020","title":"泰丰国际城","houseurl":"http:\/\/guojichengtf.fang.com\/","zongfen":"5.0","dianpingcount":1,"tao":"0","housetype":"loupan","saling":"1","purpose":"住宅","tejia":false,"xiaoguotu":"效果图","x":"113.92696380615234375000","y":"29.97366905212402343750","price_num":"3300","price_unit":"元\/平","picAddress":"http:\/\/img.soufun.com\/viewimage\/house\/2014_05\/09\/1399620188834_000\/232x162.jpg","householdpic":"<u>二居<\/u>&#10<u>三居<\/u>&#10","adshowurl":"","minarea":79,"maxarea":126,"物业类别":"普通住宅","项目特色":"湖景地产景观居所","建筑类别":"板塔结合超高层","装修状况":"毛坯","产权年限":"70","环线位置":"暂无资料","开发商":"湖北泰丰投资发展有限公司","楼盘地址":"嘉鱼县沿湖大道","销售状态":"在售","楼盘优惠":"暂无","开盘时间":"2014-4-7[开盘时间详情]","交房时间":"2016-3-31","售楼地址":"嘉鱼县沿湖大道（二乔公园对面）","咨询电话":"400-890-0000转802609","主力户型":"二居(2)三居(4)","预售许可证":"","占地面积":"315152平方米","建筑面积":"1031950平方米","容积率":"3.00 ","绿化率":"32%","停车位":"地上车位","楼栋总数":"暂无资料","总户数":"6594户","物业公司":"四川志升物业管理有限公司","物业费":"1.44元\/平方米·月 ","楼层状况":"30栋33层","70":"","2路公交车":"","小区内部配套":"幼儿园、社区卫生站、会所。","项目业态包括高层电梯公寓、商业MALL、步行街、写字楼、各种配套设施。本项目高层住宅立面为ARTDECO风格，项目内景分别为维多利亚、圣地亚哥、马尔代夫、毛里求斯四大主题景观。商业建筑面积接近20万平方米，旨在打造嘉鱼封面商业，建设成为城市休闲消费新地标，建成后将提升整个嘉鱼县的城市形象同时改变现有的商业格局。幼儿园、农贸市场、医疗站、社区服务中心等配套设施均分布在组团外部及沿街商铺中。集团致力于从硬件到软件全方位打造嘉鱼一流社区标杆，因此项目选择集团直属物业公司志升物业公司（国家二级物业管理资质），能够更改的融会贯通集团这一开发理念，全心全意为小区业主提供高标准物业服务。湖北泰丰投资发展有限公司是四川泰丰集团有限公司旗下的全资子公司，注册资金5000万元，是湖北嘉鱼政府的重点招商引资项目，嘉鱼县人民政府于2013年6月26日与四川泰丰集团有限公司签订项目协议":"","on_the_average":"均价约3300元\/平方米","house_type":1}]