[{"newCode":"2010182684","title":"融创涌清府","houseurl":"http:\/\/yongqingfurc.fang.com\/","zongfen":"3.5","dianpingcount":25,"tao":"186","housetype":"loupan","saling":"1","purpose":"住宅","tejia":false,"xiaoguotu":"效果图","x":"120.22491455078125000000","y":"30.28230476379394531250","price_num":"52000","price_unit":"元\/平","picAddress":"http:\/\/img6n.soufunimg.com\/viewimage\/house\/2016_10\/24\/M08\/0C\/39\/wKgE2VgNeyKIbiATAAoKLXXjhMsAATGaAKsuJcACgpF559\/232x162.jpg","householdpic":"<u>三居<\/u>&#10<u>四居<\/u>&#10","adshowurl":"","minarea":125,"maxarea":147,"物业类别":"普通住宅","项目特色":"品牌地产宜居生态地产","建筑类别":"板塔结合高层","装修状况":"暂无","产权年限":"普通住宅:70年","环线位置":"暂无资料","开发商":"杭州融汇前江置业有限公司","楼盘地址":"杭州市江干区运河东路和严家弄路交叉口","销售状态":"在售","楼盘优惠":"暂无","开盘时间":"已于2017年8月15日加推6#[开盘时间详情]","交房时间":"预计2019年12月20日整体交付","售楼地址":"杭州市江干区运河东路与严家弄路交叉口西南侧","咨询电话":"400-890-0000转820900","主力户型":"三居(2)四居(6)","预售许可证":"","占地面积":"18800平方米","建筑面积":"48000平方米","容积率":"2.60 ","绿化率":"30%","停车位":"暂无资料","楼栋总数":"7栋","总户数":"342户","物业公司":"融创物业管理有限公司","物业费":"暂无资料 ","楼层状况":"共7栋，10-27层","普通住宅:70年":"","公交31路、200路章家坝站下":"","幼儿园":"浙江大学幼儿园钱江分园、杭州市人民政府机关幼儿园中小学","融创中国持续发力推进高端物业开发。杭州融创于钱江新城先后开发望江府、侯潮府两大口碑之作后，于2016年在钱江新城倾力缔造座府系产品——取意杭州古城门——涌金门、清波门，再糅合融创府系作品传承之念，为之命名“涌清府”，不仅承袭了府系产品高规格的营造标准，还将进入归心社区2.0时代，缔造更能与钱江新城的生活相接轨的全新作品——融创涌清府。融创涌清府的园林设计灵感源自书法“笔锋”，汲取新加坡知名住宅的创新景观设计精髓，一气呵成折转自如，凌厉婉转刚柔并济。整个景观系统由流线水景、游步道、立体连廊、起伏地形、巷道五条“流动的丝带”构成，疏密交织中描绘出富有特色的多重立体景观架构，与项目的不规则建筑外立面正相映成趣。建筑面积约125及148㎡纯粹改善户型，摈弃了一切只为奢侈而豪华的过度包装，而是回归以人为本的家装理念，植入科学智能元素，赋予更健康、更人性化的良心定制，为业主打造自在安住的生活境界":"","on_the_average":"均价约52000元\/平方米","house_type":1},{"newCode":"2010789482","title":"东方君悦","houseurl":"http:\/\/dongfangjunyue.fang.com\/","zongfen":"4.3","dianpingcount":206,"tao":"878","housetype":"loupan","saling":"1","purpose":["\\u5546\\u4f4f\\u697c","\\u4f4f\\u5b85"],"tejia":false,"xiaoguotu":"","x":"120.22666168212890625000","y":"30.25701522827148437500","price_num":"40000","price_unit":"元\/平","picAddress":"http:\/\/imgs.soufun.com\/viewimage\/house\/2011_06\/02\/hangzhou\/1307011151913_000\/232x162.jpg","householdpic":"<u>一居<\/u>&#10<u>二居<\/u>&#10<u>三居<\/u>&#10","adshowurl":"","minarea":168,"maxarea":168,"物业类别":"普通住宅,酒店式公寓,商住公寓","项目特色":"江景地产酒店式公寓","建筑类别":"板塔结合高层","装修状况":"非毛坯","产权年限":"普通住宅:40年酒店式公寓:40年商住公寓:40年","环线位置":"暂无资料","开发商":"浙江全景置业有限公司","楼盘地址":"钱江新城民心路与剧院路交界处（邻万象城）","销售状态":"在售","楼盘优惠":"暂无","开盘时间":"已于2011日9月18日首次开盘1、2、独#[开盘时间详情]","交房时间":"2014年1月已交付","售楼地址":"杭州钱江新城民心路与剧院路交汇处（项目现场）","咨询电话":"400-890-0000转669020","主力户型":"一居(4)二居(2)三居(1)","预售许可证":"","占地面积":"17650平方米","建筑面积":"130000平方米","容积率":"5.46 ","绿化率":"20.59%","停车位":"600余个","楼栋总数":"2栋","总户数":"900户","物业公司":"金钥匙物业公司","物业费":"7.80元\/㎡·月 ","楼层状况":"A座高34层，B座高26层","普通住宅:40年":"","酒店式公寓:40年":"","商住公寓:40年":"","公交":"9路,105路,106路，富春路民心路口公交车站","综合商场":"万象城医院","东方君悦位于钱江新城核心区，轨道交通1、2、4号线均设有站点。东方君悦与万象城、银行总部大楼集群一路相隔，众多的五星级酒店及甲级写字楼环相拥立，不仅享有钱江新城的核心商务、商业配套，更是少见的江景物业。":"","on_the_average":"均价约40000元\/平方米","house_type":1},{"newCode":"2011107094","title":"中海御道路一号","houseurl":"http:\/\/yudaoluyihaozh.fang.com\/","zongfen":"4.2","dianpingcount":339,"tao":"242","housetype":"loupan","saling":"1","purpose":"住宅","tejia":false,"xiaoguotu":"","x":"120.24068450927734375000","y":"30.27573966979980468750","price_num":"50000","price_unit":"元\/平","picAddress":"http:\/\/imgs.soufun.com\/viewimage\/house\/2013_10\/17\/hangzhou\/1382001603447_000\/232x162.jpg","householdpic":"<u>二居<\/u>&#10<u>三居<\/u>&#10<u>四居<\/u>&#10","adshowurl":"","minarea":138,"maxarea":235,"物业类别":"普通住宅","项目特色":"景观居所江景地产","建筑类别":"板楼低层多层高层超高层","装修状况":"毛坯[30套装修案例]","产权年限":"普通住宅:70年","环线位置":"暂无资料","开发商":"杭州中海宏鲲房地产有限公司","楼盘地址":"钱江新城之江路与御道路交汇处","销售状态":"在售","楼盘优惠":"暂无","开盘时间":"已于3月初加推二区3#[开盘时间详情]","交房时间":"预计2017年年底交付112-128方小户型房源","售楼地址":"江干区钱江新城之江路与御道路交汇处","咨询电话":"400-890-0000转662511","主力户型":"二居(1)三居(9)四居(2)","预售许可证":"","占地面积":"99462平方米","建筑面积":"512603平方米","容积率":"3.50 ","绿化率":"30%","停车位":"车位均位于地下室","楼栋总数":"23栋","总户数":"1476户","物业公司":"中海物业管理服务有限公司","物业费":"4.50元\/㎡·月 ","楼层状况":"中海御道路一号共23栋楼，其中共16栋29-35层高层，7栋4层多层。","普通住宅:70年":"","公交":"杭海路钱江二桥站（140路,210路,210路区间,401路）；自驾","幼儿园":"杭州市人民政府机关幼儿园（运新园区）、杭州市江干区御道幼儿园中小学","中海御道路一号,位于钱江新城之江路与御道路交叉口，距离钱塘江大约100米，从御道路一号出发，距离武林、西湖、萧山国际机场都不远。中海御道路一号在享有钱江新城十四年配套的基础上，又有钱江金融城未来汇聚的金融、生活、商业及休闲配套。":"","on_the_average":"均价约50000元\/平方米","house_type":1},{"newCode":"2011121566","title":"中企艮山府","houseurl":"http:\/\/yupinwanzq.fang.com\/","zongfen":"4.2","dianpingcount":179,"tao":"156","housetype":"loupan","saling":"1","purpose":"住宅","tejia":false,"xiaoguotu":"效果图","x":"120.22384643554687500000","y":"30.28584671020507812500","price_num":"34000","price_unit":"元\/平","picAddress":"http:\/\/imgs.soufun.com\/viewimage\/house\/2014_01\/06\/hangzhou\/1388985893086_000\/232x162.jpg","householdpic":"<u>一居<\/u>&#10<u>二居<\/u>&#10<u>三居<\/u>&#10<u>四居<\/u>&#10<u>五居<\/u>&#10","adshowurl":"","minarea":88,"maxarea":280,"物业类别":"普通住宅","项目特色":"地铁沿线豪华居住区景观居所","建筑类别":"板塔结合高层","装修状况":"非毛坯","产权年限":"普通住宅:70年","环线位置":"暂无资料","开发商":"杭州中华企业房地产发展有限公司","楼盘地址":"运河东路498号","销售状态":"在售","楼盘优惠":"暂无","开盘时间":"东区3#和西区1、2、4#已于2017年3月18日加推[开盘时间详情]","交房时间":"已于2016年11月30日交付东区1、4、5#部分房源","售楼地址":"江干区运河东路498号","咨询电话":"400-890-0000转645195","主力户型":"一居(1)二居(2)三居(2)四居(4)五居(1)","预售许可证":"","占地面积":"61737平方米","建筑面积":"222907平方米","容积率":"2.50 ","绿化率":"30%","停车位":"地面100个，地下1073个，车位配比为1","楼栋总数":"10栋","总户数":"974户","物业公司":"上海古北物业","物业费":"3.30元\/㎡·月 ","楼层状况":"共10栋，为20-24层高层住宅。层高3.15米，户型为78—280平。","普通住宅:70年":"","自驾":"秋石快速路","综合商场":"麦德龙超市、华润万家超市、乐购新塘路店、庆春银泰、万象城、来福士广场医院","中企艮山府位于江干区章家坝，地块含东西两个部分。北侧临横河港水系，西侧紧邻京杭运河，隶属于钱江新城板块，地理位置优越，环境优美，交通便捷。总用地面积61738㎡，规划总建筑面积222926.3㎡。开发商中华企业隶属上海地产集团，该项目由日本久米设计株式会社、香港AECOM景观设计公司共同设计，规划建成10幢20-24层装修成品公寓，并配备4000多平米的私家会所":"","on_the_average":"均价约34000元\/平方米","house_type":1},{"newCode":"2011168042","title":"万科大都会79号","houseurl":"http:\/\/daduhui79haowk.fang.com\/","zongfen":"3.9","dianpingcount":77,"tao":"108","housetype":"loupan","saling":"1","purpose":"住宅","tejia":false,"xiaoguotu":"效果图","x":"120.23754119873046875000","y":"30.27300834655761718750","price_num":"49695","price_unit":"元\/平","picAddress":"http:\/\/imgs.soufun.com\/viewimage\/house\/2015_07\/16\/hangzhou\/1437031125730_000\/232x162.jpg","householdpic":"<u>四居<\/u>&#10","adshowurl":"","minarea":165,"maxarea":216,"物业类别":"普通住宅","项目特色":"江景地产","建筑类别":"板塔结合高层","装修状况":"非毛坯","产权年限":"普通住宅:70年","环线位置":"暂无资料","开发商":"杭州万霆置业有限公司","楼盘地址":"钱江新城之江隧道运河东路出口","销售状态":"在售","楼盘优惠":"暂无","开盘时间":"已于2016年8月16日加推2#[开盘时间详情]","交房时间":"预计2018年5月20日整体交付","售楼地址":"钱江新城之江隧道运河东路出口","咨询电话":"400-890-0000转820614","主力户型":"四居(3)","预售许可证":"","占地面积":"21900平方米","建筑面积":"111500平方米","容积率":"3.50 ","绿化率":"30%","停车位":"715个","楼栋总数":"2栋","总户数":"328户","物业公司":"万科物业管理公司","物业费":"4.90元\/㎡·月 ","楼层状况":"共2栋，38层","普通住宅:70年":"","四堡-公交车站":"9m路,19路,126路距离楼盘约146米塘工局-公交车站","中小学":"采荷实验中学新城校区综合商场","万科大都会79号是美国耶鲁大学建筑学院院长罗伯特·斯特恩先生落子中国杭州钱江新城的第79号作品。罗伯特·斯特恩先生之外，万科地产同时还聘美国BLD室内设计事务所、美国Lifescapes景观设计公司等多家设计公司，共同操刀本项目。主力户型面积段在160-200㎡，1:1园林空间，5:1的建筑长高比。":"","on_the_average":"均价约49695元\/平方米","house_type":1},{"newCode":"2010344264","title":"宋都阳光国际","houseurl":"http:\/\/yangguanguojisd.fang.com\/","zongfen":"4.3","dianpingcount":341,"tao":"0","housetype":"loupan","saling":"2","purpose":"住宅","tejia":false,"xiaoguotu":"","x":"120.28059387207031250000","y":"30.30130577087402343750","price_num":"32000","price_unit":"元\/平","picAddress":"http:\/\/img6n.soufunimg.com\/viewimage\/house\/2016_10\/31\/M02\/0C\/84\/wKgEUVgWnTuIaILBAAzVzbAlSpEAATjsQLpiBAADNXl700\/232x162.png","householdpic":"<u>二居<\/u>&#10<u>三居<\/u>&#10<u>四居<\/u>&#10<u>五居<\/u>&#10","adshowurl":"","minarea":0,"maxarea":0,"物业类别":"普通住宅","项目特色":"江景地产","建筑类别":"板塔结合小高层高层","装修状况":"毛坯[13套装修案例]","产权年限":"普通住宅:70年","环线位置":"暂无资料","开发商":"浙江东霖房地产开发有限公司","楼盘地址":"钱江新城沿江大道与通盛路交汇处","销售状态":"待售","楼盘优惠":"暂无","开盘时间":"2016年3月26日已加推观澜苑9#[开盘时间详情]","交房时间":"2013年12月31号全部房源已交付入住","售楼地址":"江干区钱江新城沿江大道与通盛路交汇处","咨询电话":"400-890-0000转654253","主力户型":"二居(1)三居(4)四居(3)五居(3)","预售许可证":"","占地面积":"102944平方米","建筑面积":"380000平方米","容积率":"2.58 ","绿化率":"30%","停车位":"约2167个机动车位","楼栋总数":"23栋","总户数":"2000户","物业公司":"杭州宋都物业经营管理有限公司","物业费":"1.98元\/㎡·月 ","楼层状况":"宋都阳光国际共23栋楼，其中5栋12层的小高层住宅，18栋19-25层的高层住宅。","普通住宅:70年":"","杨公村":"B1、K401、K210、K525、K320、K848、K566。沿江风景大道构建快速交通网络。","综合商场":"金海城，四季青、麦德龙、万象城、城东银泰、天虹医院","宋都阳光国际位于钱江新城，经沿江大道可从项目到达万象城和市民中心。北临艮山东路，西接圆梦园别墅区，南面浩渺钱塘江江景资源。宋都阳光国际占地约10万㎡（约150亩），总建筑面积约38万平米（含地下建筑面积）；规划居住户数达2000多户。容积率2.58，绿化率30%，地块用地约成梯形，东西面宽约300米，南北深约550米，由23幢高层小高层组成。":"","on_the_average":"均价约32000元\/平方米","house_type":1},{"newCode":"2010906134","title":"杭州来福士广场","houseurl":"http:\/\/laifushiguangchanghz.fang.com\/","zongfen":"4.0","dianpingcount":6,"tao":"0","housetype":"loupan","saling":"1","purpose":"写字楼","tejia":false,"xiaoguotu":"效果图","x":"120.21920013427734375000","y":"30.25517463684082031250","price_num":"45000","price_unit":"元\/平","picAddress":"http:\/\/imgs.soufun.com\/viewimage\/house\/2014_11\/03\/hangzhou\/1414999589901_000\/232x162.jpg","householdpic":"<u>暂无资料<\/u>&#10","adshowurl":"","minarea":0,"maxarea":0,"物业类别":"普通住宅","项目特色":"江景地产","建筑类别":"板塔结合小高层高层","装修状况":"毛坯[13套装修案例]","产权年限":"普通住宅:70年","环线位置":"暂无资料","开发商":"浙江东霖房地产开发有限公司","楼盘地址":"钱江新城沿江大道与通盛路交汇处","销售状态":"待售","楼盘优惠":"暂无","开盘时间":"2016年3月26日已加推观澜苑9#[开盘时间详情]","交房时间":"2013年12月31号全部房源已交付入住","售楼地址":"江干区钱江新城沿江大道与通盛路交汇处","咨询电话":"400-890-0000转654253","主力户型":"二居(1)三居(4)四居(3)五居(3)","预售许可证":"","占地面积":"102944平方米","建筑面积":"380000平方米","容积率":"2.58 ","绿化率":"30%","停车位":"约2167个机动车位","楼栋总数":"23栋","总户数":"2000户","物业公司":"杭州宋都物业经营管理有限公司","物业费":"1.98元\/㎡·月 ","楼层状况":"宋都阳光国际共23栋楼，其中5栋12层的小高层住宅，18栋19-25层的高层住宅。","普通住宅:70年":"","杨公村":"B1、K401、K210、K525、K320、K848、K566。沿江风景大道构建快速交通网络。","综合商场":"金海城，四季青、麦德龙、万象城、城东银泰、天虹医院","宋都阳光国际位于钱江新城，经沿江大道可从项目到达万象城和市民中心。北临艮山东路，西接圆梦园别墅区，南面浩渺钱塘江江景资源。宋都阳光国际占地约10万㎡（约150亩），总建筑面积约38万平米（含地下建筑面积）；规划居住户数达2000多户。容积率2.58，绿化率30%，地块用地约成梯形，东西面宽约300米，南北深约550米，由23幢高层小高层组成。":"","on_the_average":"均价约32000元\/平方米","house_type":1},{"newCode":"2010988776","title":"百大绿城西子国际","houseurl":"http:\/\/xiziguojibdlc.fang.com\/office\/","zongfen":"4.0","dianpingcount":5,"tao":"0","housetype":"loupan","saling":"1","purpose":"写字楼","tejia":false,"xiaoguotu":"效果图","x":"120.21042633056640625000","y":"30.26499176025390625000","price_num":"35000","price_unit":"元\/平","picAddress":"http:\/\/img6n.soufunimg.com\/viewimage\/house\/2017_06\/07\/M04\/0F\/E8\/wKgEUFk3WpqIbXCnAALZ1NgY9BMAAY26gGPzc8AAtns479\/232x162.jpg","householdpic":"<u>楼层平面图<\/u>&#10","adshowurl":"","minarea":45,"maxarea":297,"物业类别":"普通住宅","项目特色":"江景地产","建筑类别":"板塔结合小高层高层","装修状况":"毛坯[13套装修案例]","产权年限":"普通住宅:70年","环线位置":"暂无资料","开发商":"浙江东霖房地产开发有限公司","楼盘地址":"钱江新城沿江大道与通盛路交汇处","销售状态":"待售","楼盘优惠":"暂无","开盘时间":"2016年3月26日已加推观澜苑9#[开盘时间详情]","交房时间":"2013年12月31号全部房源已交付入住","售楼地址":"江干区钱江新城沿江大道与通盛路交汇处","咨询电话":"400-890-0000转654253","主力户型":"二居(1)三居(4)四居(3)五居(3)","预售许可证":"","占地面积":"102944平方米","建筑面积":"380000平方米","容积率":"2.58 ","绿化率":"30%","停车位":"约2167个机动车位","楼栋总数":"23栋","总户数":"2000户","物业公司":"杭州宋都物业经营管理有限公司","物业费":"1.98元\/㎡·月 ","楼层状况":"宋都阳光国际共23栋楼，其中5栋12层的小高层住宅，18栋19-25层的高层住宅。","普通住宅:70年":"","杨公村":"B1、K401、K210、K525、K320、K848、K566。沿江风景大道构建快速交通网络。","综合商场":"金海城，四季青、麦德龙、万象城、城东银泰、天虹医院","宋都阳光国际位于钱江新城，经沿江大道可从项目到达万象城和市民中心。北临艮山东路，西接圆梦园别墅区，南面浩渺钱塘江江景资源。宋都阳光国际占地约10万㎡（约150亩），总建筑面积约38万平米（含地下建筑面积）；规划居住户数达2000多户。容积率2.58，绿化率30%，地块用地约成梯形，东西面宽约300米，南北深约550米，由23幢高层小高层组成。":"","on_the_average":"均价约32000元\/平方米","house_type":1},{"newCode":"2011071744","title":"世包国际中心","houseurl":"http:\/\/guojizhongxinsb.fang.com\/","zongfen":"3.8","dianpingcount":35,"tao":"0","housetype":"loupan","saling":"1","purpose":["\\u5546\\u4f4f\\u697c","\\u5199\\u5b57\\u697c"],"tejia":false,"xiaoguotu":"效果图","x":"120.21350860595703125000","y":"30.24407768249511718750","price_num":"37000","price_unit":"元\/平","picAddress":"http:\/\/img6n.soufunimg.com\/viewimage\/house\/2017_06\/07\/M02\/0F\/E8\/wKgEUFk3cZmIGVouAAXwtgm047QAAY3AgG8SVUABfDO255\/232x162.gif","householdpic":"<u>楼层平面图<\/u>&#10","adshowurl":"","minarea":60,"maxarea":140,"物业类别":"普通住宅","项目特色":"江景地产","建筑类别":"板塔结合小高层高层","装修状况":"毛坯[13套装修案例]","产权年限":"普通住宅:70年","环线位置":"暂无资料","开发商":"浙江东霖房地产开发有限公司","楼盘地址":"钱江新城沿江大道与通盛路交汇处","销售状态":"待售","楼盘优惠":"暂无","开盘时间":"2016年3月26日已加推观澜苑9#[开盘时间详情]","交房时间":"2013年12月31号全部房源已交付入住","售楼地址":"江干区钱江新城沿江大道与通盛路交汇处","咨询电话":"400-890-0000转654253","主力户型":"二居(1)三居(4)四居(3)五居(3)","预售许可证":"","占地面积":"102944平方米","建筑面积":"380000平方米","容积率":"2.58 ","绿化率":"30%","停车位":"约2167个机动车位","楼栋总数":"23栋","总户数":"2000户","物业公司":"杭州宋都物业经营管理有限公司","物业费":"1.98元\/㎡·月 ","楼层状况":"宋都阳光国际共23栋楼，其中5栋12层的小高层住宅，18栋19-25层的高层住宅。","普通住宅:70年":"","杨公村":"B1、K401、K210、K525、K320、K848、K566。沿江风景大道构建快速交通网络。","综合商场":"金海城，四季青、麦德龙、万象城、城东银泰、天虹医院","宋都阳光国际位于钱江新城，经沿江大道可从项目到达万象城和市民中心。北临艮山东路，西接圆梦园别墅区，南面浩渺钱塘江江景资源。宋都阳光国际占地约10万㎡（约150亩），总建筑面积约38万平米（含地下建筑面积）；规划居住户数达2000多户。容积率2.58，绿化率30%，地块用地约成梯形，东西面宽约300米，南北深约550米，由23幢高层小高层组成。":"","on_the_average":"均价约32000元\/平方米","house_type":1},{"newCode":"2011091320","title":"杭州高德置地广场ICON私邸","houseurl":"http:\/\/iconsidigdzdgz0571.fang.com\/","zongfen":"4.1","dianpingcount":41,"tao":"0","housetype":"loupan","saling":"1","purpose":"写字楼","tejia":false,"xiaoguotu":"效果图","x":"120.21422576904296875000","y":"30.24896812438964843750","price_num":"45000","price_unit":"元\/平","picAddress":"http:\/\/img6n.soufunimg.com\/viewimage\/house\/2017_06\/07\/M07\/0F\/E9\/wKgEUVk3p8aIJlm9AAUlm0MfQ6sAAY3JQMUh6kABSWz373\/232x162.jpg","householdpic":"<u>楼层平面图<\/u>&#10","adshowurl":"","minarea":300,"maxarea":500,"物业类别":"普通住宅","项目特色":"江景地产","建筑类别":"板塔结合小高层高层","装修状况":"毛坯[13套装修案例]","产权年限":"普通住宅:70年","环线位置":"暂无资料","开发商":"浙江东霖房地产开发有限公司","楼盘地址":"钱江新城沿江大道与通盛路交汇处","销售状态":"待售","楼盘优惠":"暂无","开盘时间":"2016年3月26日已加推观澜苑9#[开盘时间详情]","交房时间":"2013年12月31号全部房源已交付入住","售楼地址":"江干区钱江新城沿江大道与通盛路交汇处","咨询电话":"400-890-0000转654253","主力户型":"二居(1)三居(4)四居(3)五居(3)","预售许可证":"","占地面积":"102944平方米","建筑面积":"380000平方米","容积率":"2.58 ","绿化率":"30%","停车位":"约2167个机动车位","楼栋总数":"23栋","总户数":"2000户","物业公司":"杭州宋都物业经营管理有限公司","物业费":"1.98元\/㎡·月 ","楼层状况":"宋都阳光国际共23栋楼，其中5栋12层的小高层住宅，18栋19-25层的高层住宅。","普通住宅:70年":"","杨公村":"B1、K401、K210、K525、K320、K848、K566。沿江风景大道构建快速交通网络。","综合商场":"金海城，四季青、麦德龙、万象城、城东银泰、天虹医院","宋都阳光国际位于钱江新城，经沿江大道可从项目到达万象城和市民中心。北临艮山东路，西接圆梦园别墅区，南面浩渺钱塘江江景资源。宋都阳光国际占地约10万㎡（约150亩），总建筑面积约38万平米（含地下建筑面积）；规划居住户数达2000多户。容积率2.58，绿化率30%，地块用地约成梯形，东西面宽约300米，南北深约550米，由23幢高层小高层组成。":"","on_the_average":"均价约32000元\/平方米","house_type":1},{"newCode":"2011168244","title":"越秀维多利中心","houseurl":"http:\/\/weiduolizhongxinyx.fang.com\/","zongfen":"3.8","dianpingcount":6,"tao":"0","housetype":"loupan","saling":"1","purpose":"写字楼","tejia":false,"xiaoguotu":"","x":"120.24048614501953125000","y":"30.27447509765625000000","price_num":"27000","price_unit":"元\/平","picAddress":"http:\/\/imgs.soufun.com\/viewimage\/house\/2014_10\/10\/hangzhou\/1412933100868_000\/232x162.jpg","householdpic":"<u>楼层平面图<\/u>&#10","adshowurl":"","minarea":0,"maxarea":0,"物业类别":"普通住宅","项目特色":"江景地产","建筑类别":"板塔结合小高层高层","装修状况":"毛坯[13套装修案例]","产权年限":"普通住宅:70年","环线位置":"暂无资料","开发商":"浙江东霖房地产开发有限公司","楼盘地址":"钱江新城沿江大道与通盛路交汇处","销售状态":"待售","楼盘优惠":"暂无","开盘时间":"2016年3月26日已加推观澜苑9#[开盘时间详情]","交房时间":"2013年12月31号全部房源已交付入住","售楼地址":"江干区钱江新城沿江大道与通盛路交汇处","咨询电话":"400-890-0000转654253","主力户型":"二居(1)三居(4)四居(3)五居(3)","预售许可证":"","占地面积":"102944平方米","建筑面积":"380000平方米","容积率":"2.58 ","绿化率":"30%","停车位":"约2167个机动车位","楼栋总数":"23栋","总户数":"2000户","物业公司":"杭州宋都物业经营管理有限公司","物业费":"1.98元\/㎡·月 ","楼层状况":"宋都阳光国际共23栋楼，其中5栋12层的小高层住宅，18栋19-25层的高层住宅。","普通住宅:70年":"","杨公村":"B1、K401、K210、K525、K320、K848、K566。沿江风景大道构建快速交通网络。","综合商场":"金海城，四季青、麦德龙、万象城、城东银泰、天虹医院","宋都阳光国际位于钱江新城，经沿江大道可从项目到达万象城和市民中心。北临艮山东路，西接圆梦园别墅区，南面浩渺钱塘江江景资源。宋都阳光国际占地约10万㎡（约150亩），总建筑面积约38万平米（含地下建筑面积）；规划居住户数达2000多户。容积率2.58，绿化率30%，地块用地约成梯形，东西面宽约300米，南北深约550米，由23幢高层小高层组成。":"","on_the_average":"均价约32000元\/平方米","house_type":1},{"newCode":"2011183446","title":"交投绿城明珠国际","houseurl":"http:\/\/mingzhuguojishangwuzhongxinjj.fang.com\/","zongfen":"3.7","dianpingcount":12,"tao":"0","housetype":"loupan","saling":"1","purpose":"写字楼","tejia":false,"xiaoguotu":"效果图","x":"120.21640014648437500000","y":"30.24169540405273437500","price_num":"29000","price_unit":"元\/平","picAddress":"http:\/\/imgs.soufun.com\/viewimage\/house\/2015_01\/12\/hangzhou\/1421055877253_000\/232x162.jpg","householdpic":"<u>暂无资料<\/u>&#10","adshowurl":"","minarea":0,"maxarea":0,"物业类别":"普通住宅","项目特色":"江景地产","建筑类别":"板塔结合小高层高层","装修状况":"毛坯[13套装修案例]","产权年限":"普通住宅:70年","环线位置":"暂无资料","开发商":"浙江东霖房地产开发有限公司","楼盘地址":"钱江新城沿江大道与通盛路交汇处","销售状态":"待售","楼盘优惠":"暂无","开盘时间":"2016年3月26日已加推观澜苑9#[开盘时间详情]","交房时间":"2013年12月31号全部房源已交付入住","售楼地址":"江干区钱江新城沿江大道与通盛路交汇处","咨询电话":"400-890-0000转654253","主力户型":"二居(1)三居(4)四居(3)五居(3)","预售许可证":"","占地面积":"102944平方米","建筑面积":"380000平方米","容积率":"2.58 ","绿化率":"30%","停车位":"约2167个机动车位","楼栋总数":"23栋","总户数":"2000户","物业公司":"杭州宋都物业经营管理有限公司","物业费":"1.98元\/㎡·月 ","楼层状况":"宋都阳光国际共23栋楼，其中5栋12层的小高层住宅，18栋19-25层的高层住宅。","普通住宅:70年":"","杨公村":"B1、K401、K210、K525、K320、K848、K566。沿江风景大道构建快速交通网络。","综合商场":"金海城，四季青、麦德龙、万象城、城东银泰、天虹医院","宋都阳光国际位于钱江新城，经沿江大道可从项目到达万象城和市民中心。北临艮山东路，西接圆梦园别墅区，南面浩渺钱塘江江景资源。宋都阳光国际占地约10万㎡（约150亩），总建筑面积约38万平米（含地下建筑面积）；规划居住户数达2000多户。容积率2.58，绿化率30%，地块用地约成梯形，东西面宽约300米，南北深约550米，由23幢高层小高层组成。":"","on_the_average":"均价约32000元\/平方米","house_type":1},{"newCode":"2011258094","title":"向江来时代中心","houseurl":"http:\/\/xiangjianglaishidaizhongxin.fang.com\/","zongfen":"3.8","dianpingcount":10,"tao":"6","housetype":"loupan","saling":"1","purpose":"写字楼","tejia":false,"xiaoguotu":"效果图","x":"120.22647094726562500000","y":"30.28531074523925781250","price_num":"36000","price_unit":"元\/平","picAddress":"http:\/\/imgs.soufun.com\/viewimage\/house\/2016_06\/06\/hangzhou\/1465208510599_000\/232x162.jpg","householdpic":"<u>楼层平面图<\/u>&#10","adshowurl":"","minarea":38,"maxarea":88,"物业类别":"普通住宅","项目特色":"江景地产","建筑类别":"板塔结合小高层高层","装修状况":"毛坯[13套装修案例]","产权年限":"普通住宅:70年","环线位置":"暂无资料","开发商":"浙江东霖房地产开发有限公司","楼盘地址":"钱江新城沿江大道与通盛路交汇处","销售状态":"待售","楼盘优惠":"暂无","开盘时间":"2016年3月26日已加推观澜苑9#[开盘时间详情]","交房时间":"2013年12月31号全部房源已交付入住","售楼地址":"江干区钱江新城沿江大道与通盛路交汇处","咨询电话":"400-890-0000转654253","主力户型":"二居(1)三居(4)四居(3)五居(3)","预售许可证":"","占地面积":"102944平方米","建筑面积":"380000平方米","容积率":"2.58 ","绿化率":"30%","停车位":"约2167个机动车位","楼栋总数":"23栋","总户数":"2000户","物业公司":"杭州宋都物业经营管理有限公司","物业费":"1.98元\/㎡·月 ","楼层状况":"宋都阳光国际共23栋楼，其中5栋12层的小高层住宅，18栋19-25层的高层住宅。","普通住宅:70年":"","杨公村":"B1、K401、K210、K525、K320、K848、K566。沿江风景大道构建快速交通网络。","综合商场":"金海城，四季青、麦德龙、万象城、城东银泰、天虹医院","宋都阳光国际位于钱江新城，经沿江大道可从项目到达万象城和市民中心。北临艮山东路，西接圆梦园别墅区，南面浩渺钱塘江江景资源。宋都阳光国际占地约10万㎡（约150亩），总建筑面积约38万平米（含地下建筑面积）；规划居住户数达2000多户。容积率2.58，绿化率30%，地块用地约成梯形，东西面宽约300米，南北深约550米，由23幢高层小高层组成。":"","on_the_average":"均价约32000元\/平方米","house_type":1},{"newCode":"2011181090","title":"华润大厦","houseurl":"http:\/\/huarundasha0571.fang.com\/","zongfen":"3.8","dianpingcount":9,"tao":"0","housetype":"loupan","saling":"3","purpose":"写字楼","tejia":false,"xiaoguotu":"","x":"120.22087097167968750000","y":"30.26059341430664062500","price_num":"5","price_unit":"元\/平.天","picAddress":"http:\/\/imgs.soufun.com\/viewimage\/house\/2015_12\/02\/hangzhou\/1449037185691_000\/232x162.jpg","householdpic":"<u>暂无资料<\/u>&#10","adshowurl":"","minarea":0,"maxarea":0,"物业类别":"普通住宅","项目特色":"江景地产","建筑类别":"板塔结合小高层高层","装修状况":"毛坯[13套装修案例]","产权年限":"普通住宅:70年","环线位置":"暂无资料","开发商":"浙江东霖房地产开发有限公司","楼盘地址":"钱江新城沿江大道与通盛路交汇处","销售状态":"待售","楼盘优惠":"暂无","开盘时间":"2016年3月26日已加推观澜苑9#[开盘时间详情]","交房时间":"2013年12月31号全部房源已交付入住","售楼地址":"江干区钱江新城沿江大道与通盛路交汇处","咨询电话":"400-890-0000转654253","主力户型":"二居(1)三居(4)四居(3)五居(3)","预售许可证":"","占地面积":"102944平方米","建筑面积":"380000平方米","容积率":"2.58 ","绿化率":"30%","停车位":"约2167个机动车位","楼栋总数":"23栋","总户数":"2000户","物业公司":"杭州宋都物业经营管理有限公司","物业费":"1.98元\/㎡·月 ","楼层状况":"宋都阳光国际共23栋楼，其中5栋12层的小高层住宅，18栋19-25层的高层住宅。","普通住宅:70年":"","杨公村":"B1、K401、K210、K525、K320、K848、K566。沿江风景大道构建快速交通网络。","综合商场":"金海城，四季青、麦德龙、万象城、城东银泰、天虹医院","宋都阳光国际位于钱江新城，经沿江大道可从项目到达万象城和市民中心。北临艮山东路，西接圆梦园别墅区，南面浩渺钱塘江江景资源。宋都阳光国际占地约10万㎡（约150亩），总建筑面积约38万平米（含地下建筑面积）；规划居住户数达2000多户。容积率2.58，绿化率30%，地块用地约成梯形，东西面宽约300米，南北深约550米，由23幢高层小高层组成。":"","on_the_average":"均价约32000元\/平方米","house_type":1},{"newCode":"2010732718","title":"迪凯金座","houseurl":"http:\/\/dikaijinzuo.fang.com\/","zongfen":"3.7","dianpingcount":7,"tao":"0","housetype":"loupan","saling":"2","purpose":"写字楼","tejia":false,"xiaoguotu":"效果图","x":"120.22229766845703125000","y":"30.25396919250488281250","price_num":"待定","price_unit":"","picAddress":"http:\/\/imgs.soufun.com\/viewimage\/house\/2013_05\/20\/hangzhou\/1369042122549_000\/232x162.jpg","householdpic":"<u>楼层平面图<\/u>&#10","adshowurl":"","minarea":0,"maxarea":0,"物业类别":"普通住宅","项目特色":"江景地产","建筑类别":"板塔结合小高层高层","装修状况":"毛坯[13套装修案例]","产权年限":"普通住宅:70年","环线位置":"暂无资料","开发商":"浙江东霖房地产开发有限公司","楼盘地址":"钱江新城沿江大道与通盛路交汇处","销售状态":"待售","楼盘优惠":"暂无","开盘时间":"2016年3月26日已加推观澜苑9#[开盘时间详情]","交房时间":"2013年12月31号全部房源已交付入住","售楼地址":"江干区钱江新城沿江大道与通盛路交汇处","咨询电话":"400-890-0000转654253","主力户型":"二居(1)三居(4)四居(3)五居(3)","预售许可证":"","占地面积":"102944平方米","建筑面积":"380000平方米","容积率":"2.58 ","绿化率":"30%","停车位":"约2167个机动车位","楼栋总数":"23栋","总户数":"2000户","物业公司":"杭州宋都物业经营管理有限公司","物业费":"1.98元\/㎡·月 ","楼层状况":"宋都阳光国际共23栋楼，其中5栋12层的小高层住宅，18栋19-25层的高层住宅。","普通住宅:70年":"","杨公村":"B1、K401、K210、K525、K320、K848、K566。沿江风景大道构建快速交通网络。","综合商场":"金海城，四季青、麦德龙、万象城、城东银泰、天虹医院","宋都阳光国际位于钱江新城，经沿江大道可从项目到达万象城和市民中心。北临艮山东路，西接圆梦园别墅区，南面浩渺钱塘江江景资源。宋都阳光国际占地约10万㎡（约150亩），总建筑面积约38万平米（含地下建筑面积）；规划居住户数达2000多户。容积率2.58，绿化率30%，地块用地约成梯形，东西面宽约300米，南北深约550米，由23幢高层小高层组成。":"","on_the_average":"均价约32000元\/平方米","house_type":1},{"newCode":"2010182526","title":"迪凯城星国际","houseurl":"http:\/\/chengxingguojikd.fang.com\/","zongfen":"3.9","dianpingcount":3,"tao":"0","housetype":"loupan","saling":"2","purpose":"写字楼","tejia":false,"xiaoguotu":"效果图","x":"120.21385955810546875000","y":"30.24677658081054687500","price_num":"待定","price_unit":"","picAddress":"http:\/\/imgs.soufun.com\/viewimage\/house\/2016_08\/10\/hangzhou\/1470818864104_000\/232x162.jpg","householdpic":"<u>暂无资料<\/u>&#10","adshowurl":"","minarea":0,"maxarea":0,"物业类别":"普通住宅","项目特色":"江景地产","建筑类别":"板塔结合小高层高层","装修状况":"毛坯[13套装修案例]","产权年限":"普通住宅:70年","环线位置":"暂无资料","开发商":"浙江东霖房地产开发有限公司","楼盘地址":"钱江新城沿江大道与通盛路交汇处","销售状态":"待售","楼盘优惠":"暂无","开盘时间":"2016年3月26日已加推观澜苑9#[开盘时间详情]","交房时间":"2013年12月31号全部房源已交付入住","售楼地址":"江干区钱江新城沿江大道与通盛路交汇处","咨询电话":"400-890-0000转654253","主力户型":"二居(1)三居(4)四居(3)五居(3)","预售许可证":"","占地面积":"102944平方米","建筑面积":"380000平方米","容积率":"2.58 ","绿化率":"30%","停车位":"约2167个机动车位","楼栋总数":"23栋","总户数":"2000户","物业公司":"杭州宋都物业经营管理有限公司","物业费":"1.98元\/㎡·月 ","楼层状况":"宋都阳光国际共23栋楼，其中5栋12层的小高层住宅，18栋19-25层的高层住宅。","普通住宅:70年":"","杨公村":"B1、K401、K210、K525、K320、K848、K566。沿江风景大道构建快速交通网络。","综合商场":"金海城，四季青、麦德龙、万象城、城东银泰、天虹医院","宋都阳光国际位于钱江新城，经沿江大道可从项目到达万象城和市民中心。北临艮山东路，西接圆梦园别墅区，南面浩渺钱塘江江景资源。宋都阳光国际占地约10万㎡（约150亩），总建筑面积约38万平米（含地下建筑面积）；规划居住户数达2000多户。容积率2.58，绿化率30%，地块用地约成梯形，东西面宽约300米，南北深约550米，由23幢高层小高层组成。":"","on_the_average":"均价约32000元\/平方米","house_type":1}]