[{"newCode":"2229222524","title":"江滨观邸","houseurl":"http:\/\/jiangbinguandi.fang.com\/","zongfen":"0.0","dianpingcount":0,"tao":"0","housetype":"loupan","saling":"1","purpose":"住宅","tejia":false,"xiaoguotu":"","x":"119.54711151123046875000","y":"26.20103836059570312500","price_num":"9500","price_unit":"元\/平","picAddress":"http:\/\/imgs.soufun.com\/viewimage\/house\/2015_08\/12\/lianjiang\/1439356659538_000\/232x162.jpg","householdpic":"","adshowurl":"","minarea":0,"maxarea":0,"物业类别":"普通住宅","项目特色":"暂无","建筑类别":"板楼","装修状况":"毛坯","产权年限":"70","环线位置":"暂无资料","开发商":"暂无资料","楼盘地址":"连江县八一六东路与八一六南路交叉口","销售状态":"在售","楼盘优惠":"暂无","开盘时间":"暂无资料[开盘时间详情]","交房时间":"","售楼地址":"连江县八一六东路与八一六南路交叉口","咨询电话":"400-890-0000转824732","主力户型":"暂无资料","预售许可证":"暂无资料","占地面积":"暂无资料","建筑面积":"107523平方米","容积率":"1.95 ","绿化率":"35%","停车位":"有206个","楼栋总数":"暂无资料","总户数":"暂无资料","物业公司":"暂无资料","物业费":"1.50元\/平方米·月 ","楼层状况":"","70":"","1路、2路、5路、9路":"","小区内部配套":"幼儿园","本项目位于福州市连江县核心桶街区，占地45600㎡。是县城少有的江景小区，南倚敖江，北临县委政府，西接八一六南路，商业繁华，街道热闹。县图书馆、江滨公园、连江一中，金字塔影城，教育、文化配套丰富。建筑上采用新古典主义融合ArtDeco建筑风格，以国际领先的真实材料作为墙面外挂，每寸立面皆手工打磨而成。保证社区内部空间的安全和完整，外滩采用了人车分流的设计，使户均1.2的配比车位，尽藏社区地下。率先引入的国际智能家居系统，在满足业主生活惬意的同时，保障了居家的安全。":"","on_the_average":"均价约9500元\/平方米","house_type":1},{"newCode":"2229224374","title":"外滩1号珑庭","houseurl":"http:\/\/waitanyihao0591.fang.com\/","zongfen":"0.0","dianpingcount":0,"tao":"0","housetype":"loupan","saling":"1","purpose":"住宅","tejia":false,"xiaoguotu":"效果图","x":"119.54502868652343750000","y":"26.19534873962402343750","price_num":"8600","price_unit":"元\/平","picAddress":"http:\/\/imgs.soufun.com\/viewimage\/house\/2015_08\/12\/lianjiang\/1439349616177_000\/232x162.jpg","householdpic":"<u>四居<\/u>&#10","adshowurl":"","minarea":172,"maxarea":172,"物业类别":"普通住宅","项目特色":"暂无","建筑类别":"板楼多层高层","装修状况":"毛坯","产权年限":"70","环线位置":"暂无资料","开发商":"福建华庆房地产公司","楼盘地址":"连江县南江滨西路1号","销售状态":"在售","楼盘优惠":"暂无","开盘时间":"暂无资料[开盘时间详情]","交房时间":"","售楼地址":"连江县南江滨西路1号","咨询电话":"400-890-0000转824757","主力户型":"四居(1)","预售许可证":"暂无资料","占地面积":"140000平方米","建筑面积":"110000平方米","容积率":"2.88 ","绿化率":"30%","停车位":"有，425","楼栋总数":"暂无资料","总户数":"暂无资料","物业公司":"暂无资料","物业费":"1.00元\/平方米·月 ","楼层状况":"7栋高层住宅和2栋临江景观洋房","70":"","1":"","小区内部配套":"幼儿园，游泳池","外滩1号珑庭是由福建华庆房地产公司鼎力开发的品质规模社区。项目位于南江滨大道，处于的江南乡的核心地段。历史悠久的名校华侨中学与项目仅一街之隔。外滩1号珑庭总用地面积为140000平方米，总建筑面积约为11万平米，规划有7栋高层住宅和2栋临江景观洋房，其中住宅建筑面积为7.5万平米，商业面积约4000平米。项目容积率仅2.88，具有较高的居住舒适度，而高达30%以上的绿化率，使得项目成为了名副其实的品质宜居楼盘。在产品方面，项目有着丰富的产品线，产品区间包括50—142平方米的一房至四房，产品类型涵盖了公寓、多层洋房和高层景观华宅，能满足不同客户的居住需求。":"","on_the_average":"均价约8600元\/平方米","house_type":1}]