[{"newCode":"1522817449","title":"兴泰・鄂尔多斯中心商务广场","houseurl":"http:\/\/eerduosizhongxinshangwuguangcxhang.fang.com\/","zongfen":"3.6","dianpingcount":2,"tao":"0","housetype":"loupan","saling":"1","purpose":"住宅","tejia":false,"xiaoguotu":"效果图","x":"98.67263031005859375000","y":"36.90236663818359375000","price_num":"待定","price_unit":"","picAddress":"http:\/\/imgs.soufun.com\/viewimage\/house\/2016_06\/13\/erduosi\/1465803900663_000\/232x162.jpg","householdpic":"<u>二居<\/u>&#10","adshowurl":"","minarea":90,"maxarea":90,"物业类别":"普通住宅","项目特色":"暂无","建筑类别":"板楼高层","装修状况":"毛坯","产权年限":"70","环线位置":"暂无资料","开发商":"内蒙古兴泰房地产开发有限责任公司","楼盘地址":"乌兰木伦河南岸中心商务区","销售状态":"在售","楼盘优惠":"暂无","开盘时间":"暂无资料[开盘时间详情]","交房时间":"","售楼地址":"暂无资料","咨询电话":"400-890-0000转828412","主力户型":"二居(1)","预售许可证":"暂无资料","占地面积":"暂无资料","建筑面积":"670000平方米","容积率":"2.30 ","绿化率":"41%","停车位":"人车分流","楼栋总数":"暂无资料","总户数":"暂无资料","物业公司":"兴泰物业公司","物业费":"2.10元\/平方米·月 ","楼层状况":"","70":"","出租车，21路、K22路":"","小区内部配套":"小型超市","兴泰·鄂尔多斯中心商务广场位于阿勒腾席热镇区的乌兰木伦河南岸中心商务区，地理位置优越，南北通透，户型好。周边环境优美，配套设施齐全。":"","on_the_average":"待定","house_type":1},{"newCode":"1522711473","title":"鄂尔多斯广场","houseurl":"http:\/\/guangchangeeds.fang.com\/office\/","zongfen":"4.1","dianpingcount":3,"tao":"0","housetype":"loupan","saling":"1","purpose":"写字楼","tejia":false,"xiaoguotu":"","x":"110.01304626464843750000","y":"39.81627273559570312500","price_num":"12000","price_unit":"元\/平","picAddress":"http:\/\/img.soufun.com\/viewimage\/house\/2012_09\/18\/erduosi\/1347949839142_000\/232x162.jpg","householdpic":"<u>暂无资料<\/u>&#10","adshowurl":"","minarea":0,"maxarea":0,"物业类别":"写字楼","项目特色":"暂无","建筑类别":"暂无资料","装修状况":"非毛坯","产权年限":"暂无","环线位置":"暂无资料","开发商":"宏大地产","楼盘地址":"鄂尔多斯市东胜区大广场西侧","销售状态":"在售","楼盘优惠":"暂无","开盘时间":"2011-04-05[开盘时间详情]","交房时间":"2011-12-01","售楼地址":"东胜大广场西侧","咨询电话":"400-890-0000转637068","主力户型":"暂无资料","预售许可证":"暂无资料","占地面积":"52000平方米","建筑面积":"300000平方米","容积率":"6.00 ","绿化率":"39%","停车位":"暂无资料","楼栋总数":"暂无资料","总户数":"暂无资料","物业公司":"暂无资料","物业费":"4.90元\/平方米·月 ","楼层状况":"共23层","暂无":"","大广场北侧，伊克昭公园西侧":"","其他":"大广场北侧、伊克昭公园","鄂尔多斯广场，位于鄂尔多斯广场西侧，伊金霍洛街与准格尔路交汇处，总建筑面积约300000平米，本项目是集大型购物中心、商业街区、写字楼、星级酒店、非毛坯loft公寓与高档平层公寓与一体的城市综合体，鄂尔多斯广场以百米高的建筑群落，汲取国际化都市中心广场精髓，倾力打造鄂尔多斯名片和城市地标。欲望都市，繁华与喧嚣的表象，难掩对空间及绿色的眷恋。寸土寸金的都市核心，肥马轻裘，香车贵妇。茂密树影中间隐约的现代建筑，阳光穿过遒劲的老槐树，青松随风摇晃。鄂尔多斯广场建筑集群紧邻都市的公园——12万平方米的伊克昭公园，在这个喧腾的都市里，难得静与繁华交汇在一起。":"","on_the_average":"均价约12000元\/平方米","house_type":1}]