[{"newCode":"2220172986","title":"宝洋壹号","houseurl":"http:\/\/baoyangyihao.fang.com\/","zongfen":"4.0","dianpingcount":1,"tao":"0","housetype":"loupan","saling":"1","purpose":"住宅","tejia":false,"xiaoguotu":"","x":"118.98973846435546875000","y":"26.91451835632324218750","price_num":"6200","price_unit":"元\/平","picAddress":"http:\/\/imgs.soufun.com\/viewimage\/house\/2014_10\/21\/ningde\/1413855839557_000\/232x162.jpg","householdpic":"<u>三居<\/u>&#10","adshowurl":"","minarea":60,"maxarea":60,"物业类别":"普通住宅","项目特色":"不限购","建筑类别":"板塔结合多层小高层","装修状况":"毛坯","产权年限":"普通住宅:70年","环线位置":"暂无资料","开发商":"屏南圣朝投资有限公司","楼盘地址":"新公安局对面","销售状态":"在售","楼盘优惠":"暂无","开盘时间":"2016-03-12[开盘时间详情]","交房时间":"","售楼地址":"屏南县新公安局对面","咨询电话":"400-890-0000转810493","主力户型":"三居(1)","预售许可证":"暂无资料","占地面积":"18717平方米","建筑面积":"23123平方米","容积率":"2.60 ","绿化率":"30%","停车位":"总共有机动车位246个，其中地面机动车位77个，地下机动车位169个。","楼栋总数":"暂无资料","总户数":"299户","物业公司":"暂无资料","物业费":"暂无资料 ","楼层状况":"","普通住宅:70年":"","邻屏南新汽车站，外出方便，沿线有3路公交车经过。位于国宝路与长汾中路交叉处，出城进城十分方便。":"","小区内部配套":"城东公园","宝洋壹号屏南城市生活广场、商业、住宅、酒店为一体。建筑面积为23123.46平方米，容积率为2.6%，绿地率为30%":"","on_the_average":"均价约6200元\/平方米","house_type":1},{"newCode":"2220172122","title":"凤凰城","houseurl":"http:\/\/fenghuangcheng0593.fang.com\/","zongfen":"0.0","dianpingcount":0,"tao":"0","housetype":"loupan","saling":"2","purpose":"住宅","tejia":false,"xiaoguotu":"效果图","x":"118.99032592773437500000","y":"26.90413093566894531250","price_num":"4800","price_unit":"元\/平","picAddress":"http:\/\/imgs.soufun.com\/viewimage\/house\/2014_10\/13\/ningde\/1413170208838_000\/232x162.jpg","householdpic":"","adshowurl":"","minarea":0,"maxarea":0,"物业类别":"普通住宅","项目特色":"暂无","建筑类别":"塔楼多层小高层","装修状况":"暂无","产权年限":"70","环线位置":"暂无资料","开发商":"屏南泰润置业发展有限公司","楼盘地址":"城南路1号（原铁合金厂）","销售状态":"待售","楼盘优惠":"暂无","开盘时间":"暂无资料[开盘时间详情]","交房时间":"","售楼地址":"屏南县环城路民政局附近","咨询电话":"400-890-0000转810170","主力户型":"暂无资料","预售许可证":"暂无资料","占地面积":"16000平方米","建筑面积":"55000平方米","容积率":"2.80 ","绿化率":"30%","停车位":"机动车位123个","楼栋总数":"暂无资料","总户数":"248户","物业公司":"暂无资料","物业费":"0.70元\/平方米·月 ","楼层状况":"9-18F","70":"","屏南汽车站1路、三路公交车":"","暂无资料":"","屏南凤凰城小区地处屏南县城南路1号，依托城市主干道东环中路与翠屏南路迅捷出行。小区占地约1.6万平方米，总建筑面积约5.5万平方米，由4栋9-18F风景高层和1栋三星级豪华酒店组成，采用紧随时代潮流的现代主义建筑风格，时尚而典雅，内敛而高贵。倾情打造八大智能化管理系统，让您享受高品质的智能化生活。小区凭借周边山林，古夏溪、采光地下停车场、中庭花园、架空层泛会所、双排众景电梯、入户花园，营造出七重立体景观。届时，古夏溪沿岸将进行景观改造，打造成一条可供业主观景、休憩的水岸景观带，达到“园中有景、景中有园”德立体景观体系。":"","on_the_average":"均价约4800元\/平方米","house_type":1}]